yaml2dataclass/__init__.py
yaml2dataclass-0.3.3.dist-info/LICENSE
yaml2dataclass-0.3.3.dist-info/METADATA
yaml2dataclass-0.3.3.dist-info/WHEEL
yaml2dataclass-0.3.3.dist-info/top_level.txt
yaml2dataclass-0.3.3.dist-info/RECORD
